ok_cart/__init__.py
ok_cart/admin.py
ok_cart/apps.py
ok_cart/consts.py
ok_cart/entities.py
ok_cart/exceptions.py
ok_cart/handlers.py
ok_cart/models.py
ok_cart/pipelines.py
ok_cart/querysets.py
ok_cart/selectors.py
ok_cart/session_store.py
ok_cart/settings.py
ok_cart/api/__init__.py
ok_cart/api/fields.py
ok_cart/api/serializers.py
ok_cart/api/urls.py
ok_cart/api/utils.py
ok_cart/api/views.py
ok_cart/migrations/0001_initial.py
ok_cart/migrations/__init__.py
ok_cart/services/__init__.py
ok_cart/services/calculations.py
ok_cart/services/cart.py
ok_cart/services/cart_group.py
ok_cart/services/cart_item.py
ok_cart/services/merge.py
django_ok_cart-0.0.5.dist-info/LICENSE
django_ok_cart-0.0.5.dist-info/METADATA
django_ok_cart-0.0.5.dist-info/WHEEL
django_ok_cart-0.0.5.dist-info/top_level.txt
django_ok_cart-0.0.5.dist-info/RECORD
