Metadata-Version: 2.1
Name: django-ok-cart
Version: 0.0.5
Summary: Django Cart.
Home-page: https://github.com/LowerDeez/ok-cart
Author: Oleg Kleschunov
Author-email: igorkleschunov@gmail.com
License: MIT
Keywords: python,django,cart,e-commerce
Platform: UNKNOWN
Classifier: Development Status :: 4 - Beta
Classifier: Environment :: Web Environment
Classifier: Intended Audience :: Developers
Classifier: License :: OSI Approved :: MIT License
Classifier: Operating System :: OS Independent
Classifier: Programming Language :: Python
Classifier: Programming Language :: Python :: 3.6
Classifier: Programming Language :: Python :: 3.7
Classifier: Programming Language :: Python :: 3.8
Classifier: Framework :: Django
Classifier: Framework :: Django :: 2.2
Classifier: Framework :: Django :: 3.1
License-File: LICENSE
Requires-Dist: django (>=2.2)
Requires-Dist: six
Requires-Dist: mock
